lribeiro.cherrypy.templating-1.0.1-py3.4-nspkg.pth
lribeiro/cherrypy/templating/__init__.py
lribeiro/cherrypy/templating/templating.py
lribeiro.cherrypy.templating-1.0.1.dist-info/WHEEL
lribeiro.cherrypy.templating-1.0.1.dist-info/top_level.txt
lribeiro.cherrypy.templating-1.0.1.dist-info/DESCRIPTION.rst
lribeiro.cherrypy.templating-1.0.1.dist-info/namespace_packages.txt
lribeiro.cherrypy.templating-1.0.1.dist-info/METADATA
lribeiro.cherrypy.templating-1.0.1.dist-info/metadata.json
lribeiro.cherrypy.templating-1.0.1.dist-info/RECORD
